source.v
`timescale 1ns / 1ns

module encoder(y, x);

  output reg [2:0] y;
  input [6:0] x;

  always @(*) begin
    y = x[6] + x[5] + x[4] + x[3] + x[2] + x[1] + x[0];
  end
  
endmodule


module mux(z, y, s);

  output reg z;
  input [2:0] y;
  input [1:0] s;

  always @(*) begin
    case(s)
      2'b00: z = (y == 3'b000) ? 1 : 0;
      2'b01: z = (y == 3'b001) ? 1 : 0;
      2'b10: z = (y == 3'b010) ? 1 : 0;
      2'b11: z = (y == 3'b011) ? 1 : 0;
    endcase
  end
  
endmodule

testbenchEncoder.v
`timescale 1ns / 1ns
module testbench();

reg [6:0] x;
wire [2:0] yy;

encoder enc(yy, x);

initial begin
    $dumpfile("TimingDiagramEncoder.vcd");
    $dumpvars(0, yy, x);
    	
    x = 7'b0000000;
    #20;
    x = 7'b0000001;
    #20;
    x = 7'b0010010;
    #20;
    x = 7'b1010001;
    #20;
    x = 7'b0001111;
    #20;
    x = 7'b1001111;
    #20;
    x = 7'b1111101;
    #20;
    x = 7'b1111111;
    #20;	
    $finish;
end

endmodule

TimingDiagramEncoder.vcd
$date
	Thu Apr 13 11:27:47 2023
$end
$version
	Icarus Verilog
$end
$timescale
	1ns
$end
$scope module testbench $end
$var wire 3 ! yy [2:0] $end
$upscope $end
$scope module testbench $end
$var reg 7 " x [6:0] $end
$upscope $end
$enddefinitions $end
$comment Show the parameter values. $end
$dumpall
$end
#0
$dumpvars
b0 "
b0 !
$end
#20
b1 !
b1 "
#40
b10 !
b10010 "
#60
b11 !
b1010001 "
#80
b100 !
b1111 "
#100
b101 !
b1001111 "
#120
b110 !
b1111101 "
#140
b111 !
b1111111 "
